graphene_gino/__init__.py
graphene_gino/converter.py
graphene_gino/fields.py
graphene_gino/filtering.py
graphene_gino/logging.py
graphene_gino/mutations.py
graphene_gino/ordering.py
graphene_gino/pagination.py
graphene_gino/registry.py
graphene_gino/resolvers.py
graphene_gino/types.py
graphene_gino/utils.py
graphene_gino-0.2.1.dist-info/LICENSE
graphene_gino-0.2.1.dist-info/METADATA
graphene_gino-0.2.1.dist-info/WHEEL
graphene_gino-0.2.1.dist-info/top_level.txt
graphene_gino-0.2.1.dist-info/RECORD
